README.txt
embedc.py
setup.py
test.py
embedc.egg-info/PKG-INFO
embedc.egg-info/SOURCES.txt
embedc.egg-info/dependency_links.txt
embedc.egg-info/top_level.txt