Metadata-Version: 1.0
Name: embedc
Version: 0.21
Summary: Python Embedded C
Home-page: http://pyembedc.sourceforge.net
Author: Fernando Trias
Author-email: sub@trias.org
License: UNKNOWN
Platform: UNKNOWN
